vtornik.py
vtornik-0.0.3.dist-info/WHEEL
vtornik-0.0.3.dist-info/METADATA
vtornik-0.0.3.dist-info/RECORD
